pyplunet/__init__.py
pyplunet/client.py
pyplunet/enums.py
pyplunet/exceptions.py
pyplunet/models.py
pyplunet/retrying_client.py
pyplunet/services/__init__.py
pyplunet/services/data_admin30.py
pyplunet/services/data_credit_note30.py
pyplunet/services/data_custom_fields30.py
pyplunet/services/data_customer30.py
pyplunet/services/data_customer_address30.py
pyplunet/services/data_customer_contact30.py
pyplunet/services/data_document30.py
pyplunet/services/data_item30.py
pyplunet/services/data_job30.py
pyplunet/services/data_job_round30.py
pyplunet/services/data_order30.py
pyplunet/services/data_outgoing_invoice30.py
pyplunet/services/data_payable30.py
pyplunet/services/data_quote30.py
pyplunet/services/data_request30.py
pyplunet/services/data_resource30.py
pyplunet/services/data_resource_address30.py
pyplunet/services/data_resource_contact30.py
pyplunet/services/data_user30.py
pyplunet/services/report_customer30.py
pyplunet/services/report_job30.py
pyplunet/services/request_doc_text30.py
pyplunet-0.11.1.dist-info/LICENSE
pyplunet-0.11.1.dist-info/METADATA
pyplunet-0.11.1.dist-info/WHEEL
pyplunet-0.11.1.dist-info/top_level.txt
pyplunet-0.11.1.dist-info/RECORD
