Metadata-Version: 2.1
Name: pyplunet
Version: 0.11.1
Summary: Client for the Plunet 3.0 SOAP API.
Author-email: Henrik Kühnemann <hello@yellownape.se>
License: Copyright © 2024 Henrik Kühnemann
Project-URL: Homepage, https://github.com/kuhnemann/pyplunet
Keywords: plunet,api,translation,localization,tms
Classifier: License :: OSI Approved :: MIT License
Classifier: Programming Language :: Python
Classifier: Programming Language :: Python :: 3
Requires-Python: >=3.10
License-File: LICENSE
Requires-Dist: plunetapi>=0.4
Requires-Dist: pydantic<3.0.0,>=2.0.0
Provides-Extra: dev
Requires-Dist: black; extra == "dev"
Requires-Dist: bumpver; extra == "dev"
Requires-Dist: isort; extra == "dev"
Requires-Dist: pip-tools; extra == "dev"
Requires-Dist: pytest; extra == "dev"
